boringproxy_api/__init__.py
boringproxy_api/boringproxy_api.py
boringproxy_api-0.2.3.dist-info/LICENSE
boringproxy_api-0.2.3.dist-info/METADATA
boringproxy_api-0.2.3.dist-info/WHEEL
boringproxy_api-0.2.3.dist-info/top_level.txt
boringproxy_api-0.2.3.dist-info/RECORD
